LICENSE
MANIFEST.in
README.rst
setup.py
astro_snail.egg-info/PKG-INFO
astro_snail.egg-info/SOURCES.txt
astro_snail.egg-info/dependency_links.txt
astro_snail.egg-info/requires.txt
astro_snail.egg-info/top_level.txt
snail/AccessArchivalData.py
snail/PhaseEstimate.py
snail/Predict.py
snail/SpecProc.py
snail/Train.py
snail/__init__.py
snail/utils/GPLightCurve.py
snail/utils/SpecFPCA.py
snail/utils/SpecGSmooth.py
snail/utils/SyntheticPhot.py
snail/utils/__init__.py
snail/utils/helper/HsiaoTemplate.csv
snail/utils/helper/fpca_basis/B0_CataSolve.csv
snail/utils/helper/fpca_basis/B0_FPCA_Application.R
snail/utils/helper/fpca_basis/B0_ReqGrid.csv
snail/utils/helper/fpca_basis/B0_SoEfunc.csv
snail/utils/helper/fpca_basis/B0_SoErrvar.csv
snail/utils/helper/fpca_basis/B0_SoEval.csv
snail/utils/helper/fpca_basis/B0_SoFittedMean.csv
snail/utils/helper/fpca_basis/B1_CataSolve.csv
snail/utils/helper/fpca_basis/B1_FPCA_Application.R
snail/utils/helper/fpca_basis/B1_ReqGrid.csv
snail/utils/helper/fpca_basis/B1_SoEfunc.csv
snail/utils/helper/fpca_basis/B1_SoErrvar.csv
snail/utils/helper/fpca_basis/B1_SoEval.csv
snail/utils/helper/fpca_basis/B1_SoFittedMean.csv
snail/utils/helper/transmission_curves/B(CSP-Swope).txt
snail/utils/helper/transmission_curves/B(Cfa-1.2-new).txt
snail/utils/helper/transmission_curves/B(Cfa-1.2-old).txt
snail/utils/helper/transmission_curves/B(Swift-UVOT).txt
snail/utils/helper/transmission_curves/B(kait1).txt
snail/utils/helper/transmission_curves/B(kait2).txt
snail/utils/helper/transmission_curves/B(kait3).txt
snail/utils/helper/transmission_curves/B(kait4).txt
snail/utils/helper/transmission_curves/B(nickel1).txt
snail/utils/helper/transmission_curves/B(nickel2).txt
snail/utils/helper/transmission_curves/I(Cfa-1.2-new).txt
snail/utils/helper/transmission_curves/I(Cfa-1.2-old).txt
snail/utils/helper/transmission_curves/I(kait1).txt
snail/utils/helper/transmission_curves/I(kait2).txt
snail/utils/helper/transmission_curves/I(kait3).txt
snail/utils/helper/transmission_curves/I(kait4).txt
snail/utils/helper/transmission_curves/I(nickel1).txt
snail/utils/helper/transmission_curves/I(nickel2).txt
