Metadata-Version: 2.1
Name: astro-snail
Version: 1.1.3
Summary: SuperNova Artificial Inference by Lstm neural networks (SNAIL)
Download-URL: https://github.com/thomasvrussell/snail
Author: Lei Hu
Author-email: hulei@pmo.ac.cn
Maintainer: Lei Hu
Maintainer-email: hulei@pmo.ac.cn
License: MIT Licence
Classifier: Development Status :: 4 - Beta
Classifier: Environment :: Console
Classifier: Intended Audience :: Science/Research
Classifier: Natural Language :: English
Classifier: Programming Language :: Python :: 3.6
Classifier: Programming Language :: Python :: 3 :: Only
Classifier: Topic :: Scientific/Engineering :: Astronomy
License-File: LICENSE
